sortedintersect/__init__.py
sortedintersect/sintersect.cpython-310-darwin.so
sortedintersect/sintersect.hpp
sortedintersect/sintersect.pyx
sortedintersect-0.4.3.dist-info/LICENSE.md
sortedintersect-0.4.3.dist-info/METADATA
sortedintersect-0.4.3.dist-info/WHEEL
sortedintersect-0.4.3.dist-info/top_level.txt
sortedintersect-0.4.3.dist-info/RECORD
