Metadata-Version: 2.1
Name: sortedintersect
Version: 0.4.3
Summary: Interval intersection for sorted query and target intervals
Author: Kez Cleal
Author-email: Kez Cleal <clealk@cardiff.ac.uk>
License-File: LICENSE.md
